LICENSE
pydrugshortagesca/__init__.py
pydrugshortagesca/api.py
pydrugshortagesca/cli.py
pydrugshortagesca/export.py
pydrugshortagesca-0.1.3.dist-info/entry_points.txt
pydrugshortagesca-0.1.3.dist-info/LICENSE
pydrugshortagesca-0.1.3.dist-info/WHEEL
pydrugshortagesca-0.1.3.dist-info/METADATA
pydrugshortagesca-0.1.3.dist-info/RECORD
