Metadata-Version: 2.1
Name: pydrugshortagesca
Version: 0.1.3
Summary: Minimal Python wrapper for the drugshortagescanada.ca database API
Home-page: https://github.com/pipitone/pydrugshortagesca
License: MIT
Author: Jon Pipitone
Author-email: jon@pipitone.ca
Requires-Python: >=3.7,<4.0
Classifier: License :: OSI Approved :: MIT License
Classifier: Programming Language :: Python :: 3
Classifier: Programming Language :: Python :: 3.7
Classifier: Programming Language :: Python :: 3.8
Requires-Dist: click (>=7.0,<8.0)
Requires-Dist: click_config_file (>=0.5.0,<0.6.0)
Requires-Dist: configobj (>=5.0.6,<6.0.0)
Requires-Dist: requests (>=2.22.0,<3.0.0)
Project-URL: Repository, https://github.com/pipitone/pydrugshortagesca
